teed/BULKCM.md
teed/MEAS.md
teed/__init__.py
teed/__main__.py
teed/bulkcm.py
teed/config.py
teed/meas.py
teed/assets/VERSION
teed-0.0.6.dist-info/LICENSE
teed-0.0.6.dist-info/METADATA
teed-0.0.6.dist-info/WHEEL
teed-0.0.6.dist-info/entry_points.txt
teed-0.0.6.dist-info/top_level.txt
teed-0.0.6.dist-info/RECORD
