Metadata-Version: 2.1
Name: teed
Version: 0.0.6
Summary: Telco engineering data library
Home-page: https://github.com/joaomg/teed
Author: joaomg
Author-email: joaomg@gmail.com
License: UNKNOWN
Keywords: telco data engineering,telco cm,telco pm,bulkcm,meas,mdc,ETSI,3gpp
Platform: UNKNOWN
Classifier: Development Status :: 3 - Alpha
Classifier: Environment :: Console
Classifier: Intended Audience :: Developers
Classifier: Intended Audience :: Telecommunications Industry
Classifier: License :: OSI Approved :: GNU Affero General Public License v3 or later (AGPLv3+)
Classifier: Natural Language :: English
Classifier: Operating System :: OS Independent
Classifier: Programming Language :: Python :: 3
Classifier: Programming Language :: Python :: 3.8
Classifier: Topic :: Software Development :: Libraries :: Python Modules
Classifier: Topic :: Text Processing :: Markup :: XML
Requires-Python: >=3.8
Requires-Dist: lxml (>=4.6.3)
Requires-Dist: pyyaml (>=5.4.1)
Requires-Dist: typer (>=0.3.2)
Provides-Extra: dev
Requires-Dist: black ; extra == 'dev'
Requires-Dist: pylama ; extra == 'dev'
Requires-Dist: pytest ; extra == 'dev'
Requires-Dist: pytest-cov ; extra == 'dev'
